stupiddb/__init__.py
stupiddb-1.0.dist-info/METADATA
stupiddb-1.0.dist-info/WHEEL
stupiddb-1.0.dist-info/top_level.txt
stupiddb-1.0.dist-info/RECORD
