Metadata-Version: 2.1
Name: stupiddb
Version: 1.0
Summary: The stupidest database system ever made
Home-page: https://github.com/gugu256
Author: gugu256
Author-email: gugu256@mail.com
Project-URL: GitHub Repository, https://github.com/gugu256/StupidDB
Keywords: database key value key-value KV esoteric
Classifier: Development Status :: 5 - Production/Stable
Classifier: Intended Audience :: Developers
Classifier: Programming Language :: Python :: 3
Classifier: Operating System :: Unix
Classifier: Operating System :: MacOS :: MacOS X
Classifier: Operating System :: Microsoft :: Windows
